<?xml version="1.0" encoding="utf-8" ?>
<Defs>
	<ThingDef ParentName="ResourceBase">
    	<defName>Biomes_Chitin</defName>
    	<label>chitin</label>
    	<description>A rough plated material gathered from arthropods, often used to make armor and clothing.</description>
    	<graphicData>
    	 	<texPath>Things/Resources/Chitin</texPath>
    	 	<graphicClass>Graphic_Single</graphicClass>
            <color>(213,186,142)</color>
    	</graphicData>
    	<useHitPoints>false</useHitPoints>
    	<statBases>
      		<MarketValue>2.1</MarketValue>
      		<Mass>0.5</Mass>
      		<SharpDamageMultiplier>1.1</SharpDamageMultiplier>
      		<BluntDamageMultiplier>0.5</BluntDamageMultiplier>
    	</statBases>
    	<stuffProps>
    		<statFactors>
        		<MaxHitPoints>1.1</MaxHitPoints>
        		<Beauty>0.8</Beauty>
        		<Flammability>0.3</Flammability>
    		</statFactors>
		</stuffProps>
        <comps>
            <li>
                <compClass>CompColorable</compClass>
            </li>
        </comps>
    	<thingCategories>
      		<li>ResourcesRaw</li>
    	</thingCategories>
  	</ThingDef>
</Defs>